meridian_sdk/__init__.py
meridian_sdk/client.py
meridian_sdk/exceptions.py
meridian_sdk/models.py
meridian_sdk/version.py
meridian_sdk-2.1.0.dist-info/METADATA
meridian_sdk-2.1.0.dist-info/WHEEL
meridian_sdk-2.1.0.dist-info/top_level.txt
meridian_sdk-2.1.0.dist-info/RECORD
