Metadata-Version: 2.4
Name: meridian-sdk
Version: 2.1.0
Summary: Python SDK for Meridian AI Search API - Enterprise search across connected data sources
Author-email: Meridian Team <kn@trymeridian.dev>
License: MIT
Project-URL: Homepage, https://www.trymeridian.dev
Project-URL: Documentation, https://www.trymeridian.dev/docs
Project-URL: Repository, https://github.com/trymeridian/meridian-sdk
Project-URL: Issues, https://github.com/trymeridian/meridian-sdk/issues
Keywords: meridian,api,sdk,search,ai,enterprise,rag
Classifier: Development Status :: 5 - Production/Stable
Classifier: Intended Audience :: Developers
Classifier: License :: OSI Approved :: MIT License
Classifier: Programming Language :: Python :: 3
Classifier: Programming Language :: Python :: 3.8
Classifier: Programming Language :: Python :: 3.9
Classifier: Programming Language :: Python :: 3.10
Classifier: Programming Language :: Python :: 3.11
Classifier: Programming Language :: Python :: 3.12
Classifier: Topic :: Internet :: WWW/HTTP
Classifier: Topic :: Software Development :: Libraries
Classifier: Topic :: Software Development :: Libraries :: Python Modules
Requires-Python: >=3.8
Requires-Dist: httpx>=0.24.0
Requires-Dist: pydantic>=2.0.0
Provides-Extra: dev
Requires-Dist: pytest>=7.0.0; extra == "dev"
Requires-Dist: pytest-asyncio>=0.21.0; extra == "dev"
Requires-Dist: black>=23.0.0; extra == "dev"
Requires-Dist: mypy>=1.0.0; extra == "dev"
Requires-Dist: ruff>=0.0.270; extra == "dev"
